Metadata-Version: 2.1
Name: chopin2
Version: 1.0.9.post1
Summary: Supervised Classification with Hyperdimensional Computing
Home-page: http://github.com/cumbof/chopin2
Author: Fabio Cumbo
Author-email: fabio.cumbo@gmail.com
License: LICENSE
License-File: LICENSE
Requires-Dist: numpy
Requires-Dist: pyspark
Requires-Dist: numba
